edx_search-4.4.0.dist-info/licenses/AUTHORS
edx_search-4.4.0.dist-info/licenses/LICENSE
edxsearch/__init__.py
edxsearch/settings.py
edxsearch/urls.py
edxsearch/wsgi.py
search/__init__.py
search/api.py
search/dataclasses.py
search/elastic.py
search/filter_generator.py
search/initializer.py
search/meilisearch.py
search/result_processor.py
search/search_engine_base.py
search/urls.py
search/utils.py
search/views.py
search/tests/__init__.py
search/tests/factories.py
search/tests/mock_search_engine.py
search/tests/test_api_mock_engine.py
search/tests/test_api_multi_value.py
search/tests/test_api_single_value.py
search/tests/test_api_timing_events.py
search/tests/test_course_discovery.py
search/tests/test_elasticsearch.py
search/tests/test_engines.py
search/tests/test_meilisearch.py
search/tests/test_mock_search_engine.py
search/tests/test_search_result_processor.py
search/tests/test_utils.py
search/tests/test_views.py
search/tests/tests.py
search/tests/utils.py
edx_search-4.4.0.dist-info/METADATA
edx_search-4.4.0.dist-info/WHEEL
edx_search-4.4.0.dist-info/top_level.txt
edx_search-4.4.0.dist-info/RECORD
