Metadata-Version: 2.4
Name: edx-search
Version: 4.4.0
Summary: Search and index routines for index access
Home-page: https://github.com/openedx/edx-search
Author: edX
Author-email: oscm@edx.org
License: AGPL
Classifier: Development Status :: 3 - Alpha
Classifier: Environment :: Web Environment
Classifier: Intended Audience :: Developers
Classifier: License :: OSI Approved :: GNU Affero General Public License v3
Classifier: Operating System :: OS Independent
Classifier: Programming Language :: Python :: 3
Classifier: Programming Language :: Python :: 3.11
Classifier: Programming Language :: Python :: 3.12
Classifier: Framework :: Django
Classifier: Framework :: Django :: 2.2
Classifier: Framework :: Django :: 3.0
Classifier: Framework :: Django :: 3.1
Classifier: Framework :: Django :: 3.2
Classifier: Framework :: Django :: 4.0
Classifier: Framework :: Django :: 4.2
Classifier: Framework :: Django :: 5.2
License-File: LICENSE
License-File: AUTHORS
Requires-Dist: elasticsearch<8.0.0,>=7.8.0
Requires-Dist: meilisearch
Requires-Dist: edx-toggles
Requires-Dist: Django
Requires-Dist: event-tracking
Dynamic: author
Dynamic: author-email
Dynamic: classifier
Dynamic: description
Dynamic: description-content-type
Dynamic: home-page
Dynamic: license
Dynamic: license-file
Dynamic: requires-dist
Dynamic: summary
